tesults.py
tesults-1.2.2.dist-info/LICENSE
tesults-1.2.2.dist-info/METADATA
tesults-1.2.2.dist-info/WHEEL
tesults-1.2.2.dist-info/top_level.txt
tesults-1.2.2.dist-info/RECORD
